LICENSE
MANIFEST.in
README.rst
pytimeo.py
setup.py
pytimeo.egg-info/PKG-INFO
pytimeo.egg-info/SOURCES.txt
pytimeo.egg-info/dependency_links.txt
pytimeo.egg-info/requires.txt
pytimeo.egg-info/top_level.txt