Metadata-Version: 1.1
Name: pytimeo
Version: 0.0.1
Summary: Interface between Python and SETRAM's service Timeo
Home-page: http://blog.matael.org/
Author: Mathieu (matael) Gaborit
Author-email: mathieu@matael.org
License: WTFPL
Platform: UNKNOWN
Classifier: Programming Language :: Python
Classifier: Programming Language :: Python :: 3
Classifier: Programming Language :: Python :: 3.3
Classifier: Intended Audience :: Developers
Classifier: Development Status :: 4 - Beta
